<?xml version="1.0" encoding="UTF-8"?>
<font-metrics type="TYPE0"><font-name>ChessCases</font-name><embed/><cap-height>1000</cap-height><x-height>777</x-height><ascender>1000</ascender><descender>0</descender><bbox><left>0</left><bottom>0</bottom><right>1001</right><top>1000</top></bbox><flags>33</flags><stemv>0</stemv><italicangle>0</italicangle><subtype>TYPE0</subtype><multibyte-extras><cid-type>CIDFontType2</cid-type><default-width>0</default-width><bfranges><bf us="32" ue="37" gi="3"/><bf us="40" ue="43" gi="9"/><bf us="46" ue="47" gi="13"/><bf us="49" ue="53" gi="15"/><bf us="55" ue="58" gi="20"/><bf us="65" ue="66" gi="24"/><bf us="68" ue="68" gi="26"/><bf us="70" ue="70" gi="27"/><bf us="75" ue="84" gi="28"/><bf us="86" ue="88" gi="38"/><bf us="97" ue="98" gi="41"/><bf us="100" ue="100" gi="43"/><bf us="102" ue="102" gi="44"/><bf us="107" ue="116" gi="45"/><bf us="118" ue="120" gi="55"/><bf us="160" ue="160" gi="3"/><bf us="162" ue="163" gi="77"/><bf us="164" ue="164" gi="87"/><bf us="165" ue="165" gi="81"/><bf us="166" ue="166" gi="97"/><bf us="167" ue="167" gi="79"/><bf us="192" ue="192" gi="83"/><bf us="193" ue="193" gi="90"/><bf us="194" ue="194" gi="88"/><bf us="195" ue="195" gi="84"/><bf us="196" ue="197" gi="58"/><bf us="198" ue="198" gi="80"/><bf us="199" ue="199" gi="60"/><bf us="200" ue="200" gi="92"/><bf us="201" ue="201" gi="61"/><bf us="202" ue="202" gi="89"/><bf us="203" ue="203" gi="91"/><bf us="204" ue="204" gi="96"/><bf us="205" ue="207" gi="93"/><bf us="224" ue="224" gi="63"/><bf us="225" ue="225" gi="62"/><bf us="226" ue="226" gi="64"/><bf us="227" ue="227" gi="66"/><bf us="228" ue="228" gi="65"/><bf us="229" ue="229" gi="67"/><bf us="230" ue="230" gi="82"/><bf us="231" ue="231" gi="68"/><bf us="232" ue="232" gi="70"/><bf us="233" ue="233" gi="69"/><bf us="234" ue="235" gi="71"/><bf us="236" ue="236" gi="74"/><bf us="237" ue="237" gi="73"/><bf us="238" ue="239" gi="75"/><bf us="8220" ue="8221" gi="85"/><bf us="65535" ue="65535" gi="0"/></bfranges><cid-widths start-index="0"><wx w="500"/><wx w="0"/><wx w="1000"/><wx w="1000"/><wx w="1000"/><wx w="1000"/><wx w="1000"/><wx w="1000"/><wx w="1000"/><wx w="1000"/><wx w="1000"/><wx w="1000"/><wx w="1000"/><wx w="1000"/><wx w="1000"/><wx w="1000"/><wx w="1000"/><wx w="1000"/><wx w="1000"/><wx w="1000"/><wx w="1000"/><wx w="1000"/><wx w="1000"/><wx w="1000"/><wx w="1000"/><wx w="1000"/><wx w="1000"/><wx w="1000"/><wx w="1000"/><wx w="1000"/><wx w="1000"/><wx w="1000"/><wx w="1000"/><wx w="1000"/><wx w="1000"/><wx w="1000"/><wx w="1000"/><wx w="1000"/><wx w="1000"/><wx w="1000"/><wx w="1000"/><wx w="1000"/><wx w="1000"/><wx w="1000"/><wx w="1000"/><wx w="1000"/><wx w="1000"/><wx w="1000"/><wx w="1000"/><wx w="1000"/><wx w="1000"/><wx w="1000"/><wx w="1000"/><wx w="1000"/><wx w="1000"/><wx w="1000"/><wx w="1000"/><wx w="1000"/><wx w="1000"/><wx w="1000"/><wx w="1000"/><wx w="1000"/><wx w="1000"/><wx w="1000"/><wx w="1000"/><wx w="1000"/><wx w="1000"/><wx w="1000"/><wx w="1000"/><wx w="1000"/><wx w="1000"/><wx w="1000"/><wx w="1000"/><wx w="1000"/><wx w="1000"/><wx w="1000"/><wx w="1000"/><wx w="730"/><wx w="820"/><wx w="542"/><wx w="1000"/><wx w="767"/><wx w="1000"/><wx w="1000"/><wx w="1000"/><wx w="1000"/><wx w="1000"/><wx w="725"/><wx w="1000"/><wx w="1000"/><wx w="1000"/><wx w="1000"/><wx w="1000"/><wx w="1000"/><wx w="1000"/><wx w="1000"/><wx w="1000"/><wx w="623"/><wx w="0"/></cid-widths></multibyte-extras></font-metrics>